odoo10_addon_crm_location_nuts-10.0.1.0.0-py2.7-nspkg.pth
odoo/addons/crm_location_nuts/README.rst
odoo/addons/crm_location_nuts/__init__.py
odoo/addons/crm_location_nuts/__manifest__.py
odoo/addons/crm_location_nuts/i18n/es.po
odoo/addons/crm_location_nuts/models/__init__.py
odoo/addons/crm_location_nuts/models/crm_lead.py
odoo/addons/crm_location_nuts/static/description/icon.png
odoo/addons/crm_location_nuts/tests/__init__.py
odoo/addons/crm_location_nuts/tests/test_crm_location_nuts.py
odoo/addons/crm_location_nuts/views/crm_lead_view.xml
odoo10_addon_crm_location_nuts-10.0.1.0.0.dist-info/DESCRIPTION.rst
odoo10_addon_crm_location_nuts-10.0.1.0.0.dist-info/METADATA
odoo10_addon_crm_location_nuts-10.0.1.0.0.dist-info/RECORD
odoo10_addon_crm_location_nuts-10.0.1.0.0.dist-info/WHEEL
odoo10_addon_crm_location_nuts-10.0.1.0.0.dist-info/metadata.json
odoo10_addon_crm_location_nuts-10.0.1.0.0.dist-info/namespace_packages.txt
odoo10_addon_crm_location_nuts-10.0.1.0.0.dist-info/top_level.txt
